weiboRobot/__init__.py
weiboRobot/auth.py
weiboRobot/config.py
weiboRobot/ticket4code.py
weiboRobot/utils.py
weiboRobot/weiboRobot.py
weiboRobot/weiboclient.py
weiboRobot-2.0.1.dist-info/DESCRIPTION.rst
weiboRobot-2.0.1.dist-info/METADATA
weiboRobot-2.0.1.dist-info/RECORD
weiboRobot-2.0.1.dist-info/WHEEL
weiboRobot-2.0.1.dist-info/metadata.json
weiboRobot-2.0.1.dist-info/top_level.txt
