Metadata-Version: 2.0
Name: weiboRobot
Version: 2.0.1
Summary: A weibo api for sending weibo automatically
Home-page: https://github.com/haipersist/weibo
Author: Haibo Wang
Author-email: 393993705@qq.com
License: BSD
Platform: any
Classifier: Development Status :: 4 - Beta
Classifier: Environment :: Web Environment
Classifier: Intended Audience :: Developers
Classifier: License :: OSI Approved :: BSD License
Classifier: Operating System :: OS Independent
Classifier: Programming Language :: Python
Classifier: Topic :: Internet :: WWW/HTTP :: Dynamic Content
Classifier: Topic :: Software Development :: Libraries :: Python Modules
Requires-Dist: requests (>=2.8.1)
Requires-Dist: rsa
Requires-Dist: weibo
